dse_data_loader/__init__.py
dse_data_loader/dse_data_loader.py
dse_data_loader/price_plots.py
dse_data_loader-0.0.33.dist-info/LICENSE
dse_data_loader-0.0.33.dist-info/METADATA
dse_data_loader-0.0.33.dist-info/WHEEL
dse_data_loader-0.0.33.dist-info/top_level.txt
dse_data_loader-0.0.33.dist-info/RECORD
