Metadata-Version: 2.1
Name: dse-data-loader
Version: 0.0.33
Summary: This is a tool to download stock market data of Dhaka Stock Exchange.
Home-page: https://github.com/skfarhad/algo-trading/tree/master/dse_data_loader_pkg
Author: Sk Farhad
Author-email: sk.farhad.eee@gmail.com
License: UNKNOWN
Project-URL: Bug Tracker, https://github.com/skfarhad/algo-trading/issues
Platform: UNKNOWN
Classifier: Programming Language :: Python :: 3
Classifier: License :: OSI Approved :: MIT License
Classifier: Operating System :: OS Independent
Requires-Python: >=3.6
Requires-Dist: requests (==2.25.1)
Requires-Dist: pandas (==1.2.3)
Requires-Dist: scipy (==1.6.2)
Requires-Dist: beautifulsoup4 (==4.9.3)
Requires-Dist: matplotlib (==3.4.1)
Requires-Dist: mplfinance (==0.12.7a17)
Requires-Dist: pyti (==0.2.2)
Requires-Dist: tapy (==1.9.1)
